<content>
	<CREATEDATE id="DJRQ" fun="D8"></CREATEDATE>
	<FLUPRESULT1 id="SFJG1"></FLUPRESULT1>
	<FLUPRESULT2 id="SFJG2"></FLUPRESULT2>
	<FLUPRESULT3 id="SFJG3"></FLUPRESULT3>
	<ISTREATCODE></ISTREATCODE>
	<LASTERTDIAGNOSE id="ZHZD"></LASTERTDIAGNOSE>
	<LASTERTDIAGNOSEDATE id="ZHJCRQ" fun="D8"></LASTERTDIAGNOSEDATE>
	<LASTERTDIAGNOSEEMPID id="ZHJCRYBM" fun="ry"></LASTERTDIAGNOSEEMPID>
	<LASTERTDIAGNOSEEMPNAME id="ZHJCRYXM"></LASTERTDIAGNOSEEMPNAME>
	<LASTERTDIAGNOSEORGNAME id="ZHJCJGMC"></LASTERTDIAGNOSEORGNAME>
	<MODIFYDATE id="XGRQ" fun="D8"></MODIFYDATE>
	<MODIFYORGCODE id="XGJGDM" fun="jg"></MODIFYORGCODE>
	<MODIFYORGNAME id="XGJGMC"></MODIFYORGNAME>
	<PATHOLOGYDIAGNOSECODE id="ZZBLZDDM"></PATHOLOGYDIAGNOSECODE>
	<PATHOLOGYDIAGNOSENAME id="ZZBLZDMC"></PATHOLOGYDIAGNOSENAME>
	<PERSONID id="GRBJH"></PERSONID>
	<RECORDFLAG id="JLZT"></RECORDFLAG>
	<REGORGCODE id="DJJGDM" fun="jg"></REGORGCODE>
	<REGORGNAME id="DJJGMC"></REGORGNAME>
	<SCREENINGSN id="LSH"></SCREENINGSN>
	<VISITSTIME1 id="SFRQ1" fun="D8"></VISITSTIME1>
	<VISITSTIME2 id="SFRQ2" fun="D8"></VISITSTIME2>
	<VISITSTIME3 id="SFRQ3" fun="D8"></VISITSTIME3>
</content>